{"labelsByUnit":{"1":["noise","reject"],"10":["accept"],"11":["noise","reject"],"12":["accept"],"13":["accept"],"14":["accept"],"15":["accept"],"16":["accept"],"17":["noise","reject"],"18":["accept"],"19":["noise","reject"],"2":["mua"],"20":["accept"],"21":["accept"],"23":["accept"],"24":["noise","reject"],"25":["noise","reject"],"26":["accept"],"29":["accept"],"3":["accept"],"30":["accept"],"32":["noise","reject"],"33":["noise","reject"],"4":["accept"],"5":["accept"],"6":["accept"],"7":["accept"],"8":["accept"],"9":["accept"]},"mergeGroups":[[15,23,8],[10,29],[12,26],[13,16],[14,30],[18,21]]}