{"labelsByUnit":{"1":["noise"],"10":["noise"],"100":["accept"],"101":["artifact"],"102":["artifact"],"103":["accept"],"104":["noise"],"105":["accept"],"106":["accept"],"107":["noise"],"108":["artifact"],"109":["artifact"],"11":["artifact"],"110":["artifact"],"111":["artifact"],"112":["noise"],"113":["noise"],"114":["artifact"],"115":["artifact"],"116":["accept"],"117":["noise"],"118":["noise"],"119":["noise"],"12":["artifact"],"120":["noise"],"121":["artifact"],"122":["noise"],"123":["noise"],"124":["artifact"],"125":["artifact"],"126":["artifact"],"127":["artifact"],"128":["artifact"],"129":["noise"],"13":["artifact"],"130":["artifact"],"131":["artifact"],"132":["noise"],"133":["artifact"],"134":["artifact"],"14":["artifact"],"15":["artifact"],"16":["noise"],"17":["noise"],"18":["artifact"],"19":["artifact"],"2":["accept"],"20":["artifact"],"21":["noise"],"22":["noise"],"23":["reject"],"24":["artifact"],"25":["artifact"],"26":["artifact"],"27":["noise"],"28":["accept"],"29":["artifact"],"3":["artifact"],"30":["noise"],"31":["artifact"],"32":["artifact"],"33":["artifact"],"34":["artifact"],"35":["artifact"],"36":["artifact"],"37":["artifact"],"38":["artifact"],"39":["artifact"],"4":["artifact"],"40":["artifact"],"41":["artifact"],"42":["artifact"],"43":["artifact"],"44":["artifact"],"45":["artifact"],"46":["artifact"],"47":["artifact"],"48":["artifact"],"49":["artifact"],"5":["artifact"],"50":["artifact"],"51":["noise"],"52":["artifact"],"53":["accept"],"54":["noise"],"55":["noise"],"56":["reject"],"57":["noise"],"58":["reject"],"59":["accept"],"6":["noise"],"60":["accept"],"61":["accept"],"62":["accept"],"63":["reject"],"64":["accept"],"65":["reject"],"66":["accept"],"67":["noise"],"68":["accept"],"69":["accept"],"7":["accept"],"70":["noise"],"71":["artifact"],"72":["reject"],"73":["artifact"],"74":["reject"],"75":["reject"],"76":["artifact"],"77":["artifact"],"78":["artifact"],"79":["artifact"],"8":["artifact"],"80":["artifact"],"81":["artifact"],"82":["artifact"],"83":["artifact"],"84":["artifact"],"85":["artifact"],"86":["noise"],"87":["noise"],"88":["artifact"],"89":["artifact"],"9":["artifact"],"90":["artifact"],"91":["artifact"],"92":["artifact"],"93":["artifact"],"94":["artifact"],"95":["artifact"],"96":["noise"],"97":["accept"],"98":["noise"],"99":["noise"]},"mergeGroups":[[68,69]]}