{"labelsByUnit":{"1":["noise"],"10":["accept"],"101":["noise"],"103":["noise"],"104":["noise"],"105":["noise"],"108":["noise"],"112":["noise"],"113":["noise"],"116":["noise"],"117":["noise"],"13":["noise"],"14":["noise"],"15":["noise"],"16":["noise"],"18":["noise"],"2":["noise"],"20":["noise"],"21":["noise"],"23":["accept"],"24":["noise"],"25":["noise"],"26":["noise"],"27":["noise"],"28":["noise"],"29":["noise"],"3":["accept"],"30":["noise"],"31":["noise"],"32":["noise"],"34":["noise"],"35":["noise"],"36":["noise"],"37":["noise"],"4":["noise"],"40":["noise"],"41":["noise"],"42":["noise"],"43":["noise"],"44":["noise"],"45":["noise"],"46":["noise"],"47":["noise"],"48":["noise"],"49":["noise"],"50":["noise"],"52":["noise"],"53":["noise"],"54":["noise"],"57":["noise"],"58":["noise"],"59":["noise"],"6":["noise"],"61":["noise"],"62":["noise"],"63":["noise"],"7":["noise"],"75":["noise"],"77":["noise"],"8":["noise"],"84":["noise"],"85":["noise"],"86":["noise"],"9":["noise"],"91":["noise"]},"mergeGroups":[[100,102],[39,51],[70,72],[73,74],[76,78],[114,115],[95,96,97]]}